{
"meta":{"test_sets":[],"test_metrics":[],"learn_metrics":[{"best_value":"Min","name":"Logloss"}],"launch_mode":"Train","parameters":"","iteration_count":100,"learn_sets":["learn"],"name":"experiment"},
"iterations":[
{"learn":[0.5633675513],"iteration":0,"passed_time":0.007609685864,"remaining_time":0.7533589005},
{"learn":[0.4948819838],"iteration":1,"passed_time":0.01323638909,"remaining_time":0.6485830653},
{"learn":[0.4588604965],"iteration":2,"passed_time":0.01914067888,"remaining_time":0.6188819505},
{"learn":[0.4305071099],"iteration":3,"passed_time":0.02496051424,"remaining_time":0.5990523417},
{"learn":[0.409448408],"iteration":4,"passed_time":0.03063737895,"remaining_time":0.5821102},
{"learn":[0.3998147952],"iteration":5,"passed_time":0.03663691993,"remaining_time":0.5739784122},
{"learn":[0.3865978696],"iteration":6,"passed_time":0.04186058657,"remaining_time":0.5561477931},
{"learn":[0.3774460505],"iteration":7,"passed_time":0.0471558066,"remaining_time":0.5422917759},
{"learn":[0.353560408],"iteration":8,"passed_time":0.05333560477,"remaining_time":0.539282226},
{"learn":[0.3430057729],"iteration":9,"passed_time":0.05886731679,"remaining_time":0.5298058511},
{"learn":[0.3330119435],"iteration":10,"passed_time":0.06578288301,"remaining_time":0.5322433261},
{"learn":[0.3284612588],"iteration":11,"passed_time":0.07195224215,"remaining_time":0.5276497757},
{"learn":[0.3198550088],"iteration":12,"passed_time":0.07786931463,"remaining_time":0.5211254133},
{"learn":[0.3111374483],"iteration":13,"passed_time":0.08436942317,"remaining_time":0.5182693137},
{"learn":[0.3012292411],"iteration":14,"passed_time":0.09008046858,"remaining_time":0.5104559886},
{"learn":[0.2932920506],"iteration":15,"passed_time":0.09575461451,"remaining_time":0.5027117262},
{"learn":[0.2848641416],"iteration":16,"passed_time":0.1009953996,"remaining_time":0.4930951862},
{"learn":[0.2768153728],"iteration":17,"passed_time":0.1065248431,"remaining_time":0.4852798407},
{"learn":[0.2699430526],"iteration":18,"passed_time":0.1119200787,"remaining_time":0.4771329671},
{"learn":[0.2649055],"iteration":19,"passed_time":0.117462721,"remaining_time":0.469850884},
{"learn":[0.2605828247],"iteration":20,"passed_time":0.1229988458,"remaining_time":0.4627099438},
{"learn":[0.2581772747],"iteration":21,"passed_time":0.1288592013,"remaining_time":0.456864441},
{"learn":[0.2525319817],"iteration":22,"passed_time":0.1349965886,"remaining_time":0.4519451008},
{"learn":[0.2488840294],"iteration":23,"passed_time":0.140309894,"remaining_time":0.4443146643},
{"learn":[0.2458272651],"iteration":24,"passed_time":0.1461328081,"remaining_time":0.4383984243},
{"learn":[0.2449052051],"iteration":25,"passed_time":0.1514317526,"remaining_time":0.4309980652},
{"learn":[0.2434135816],"iteration":26,"passed_time":0.1568698085,"remaining_time":0.4241294821},
{"learn":[0.2370490595],"iteration":27,"passed_time":0.1625403847,"remaining_time":0.4179609893},
{"learn":[0.2340285521],"iteration":28,"passed_time":0.1677875714,"remaining_time":0.4107902611},
{"learn":[0.2316940136],"iteration":29,"passed_time":0.1729542563,"remaining_time":0.4035599313},
{"learn":[0.2242928296],"iteration":30,"passed_time":0.1788609397,"remaining_time":0.3981098336},
{"learn":[0.218762067],"iteration":31,"passed_time":0.1845149914,"remaining_time":0.3920943567},
{"learn":[0.2140064801],"iteration":32,"passed_time":0.1899407093,"remaining_time":0.3856371977},
{"learn":[0.2083071021],"iteration":33,"passed_time":0.1952016648,"remaining_time":0.3789208787},
{"learn":[0.2051048209],"iteration":34,"passed_time":0.2004363104,"remaining_time":0.3722388622},
{"learn":[0.1976160784],"iteration":35,"passed_time":0.205614079,"remaining_time":0.3655361405},
{"learn":[0.1954067534],"iteration":36,"passed_time":0.2107104075,"remaining_time":0.3587771803},
{"learn":[0.1950424823],"iteration":37,"passed_time":0.2157334627,"remaining_time":0.351986176},
{"learn":[0.1902320149],"iteration":38,"passed_time":0.2211223131,"remaining_time":0.3458579769},
{"learn":[0.1900295279],"iteration":39,"passed_time":0.2261561983,"remaining_time":0.3392342974},
{"learn":[0.187575963],"iteration":40,"passed_time":0.2310985132,"remaining_time":0.332556397},
{"learn":[0.1818488409],"iteration":41,"passed_time":0.2365039959,"remaining_time":0.3266007563},
{"learn":[0.1783951551],"iteration":42,"passed_time":0.2422097141,"remaining_time":0.3210686908},
{"learn":[0.174555243],"iteration":43,"passed_time":0.2479847336,"remaining_time":0.3156169337},
{"learn":[0.1701753],"iteration":44,"passed_time":0.2532652111,"remaining_time":0.3095463691},
{"learn":[0.1685121478],"iteration":45,"passed_time":0.2584261506,"remaining_time":0.303369829},
{"learn":[0.1662514854],"iteration":46,"passed_time":0.264529014,"remaining_time":0.2982986754},
{"learn":[0.1621011564],"iteration":47,"passed_time":0.2696249112,"remaining_time":0.2920936538},
{"learn":[0.1601312282],"iteration":48,"passed_time":0.274760206,"remaining_time":0.2859749083},
{"learn":[0.1599537789],"iteration":49,"passed_time":0.2796023592,"remaining_time":0.2796023592},
{"learn":[0.1587570837],"iteration":50,"passed_time":0.2843176516,"remaining_time":0.2731679398},
{"learn":[0.1554979758],"iteration":51,"passed_time":0.2893837138,"remaining_time":0.2671234282},
{"learn":[0.1534819367],"iteration":52,"passed_time":0.2945510157,"remaining_time":0.2612056177},
{"learn":[0.1514469675],"iteration":53,"passed_time":0.2993524214,"remaining_time":0.2550039145},
{"learn":[0.1512350864],"iteration":54,"passed_time":0.3041776653,"remaining_time":0.2488726352},
{"learn":[0.1499586464],"iteration":55,"passed_time":0.3092414264,"remaining_time":0.2429754064},
{"learn":[0.1492594692],"iteration":56,"passed_time":0.3139092235,"remaining_time":0.2368087125},
{"learn":[0.1449683289],"iteration":57,"passed_time":0.3191455786,"remaining_time":0.231105419},
{"learn":[0.1435885776],"iteration":58,"passed_time":0.324231768,"remaining_time":0.2253136015},
{"learn":[0.1402477206],"iteration":59,"passed_time":0.3294304486,"remaining_time":0.219620299},
{"learn":[0.1382746241],"iteration":60,"passed_time":0.3345143765,"remaining_time":0.2138698473},
{"learn":[0.1361187156],"iteration":61,"passed_time":0.3395748296,"remaining_time":0.2081265085},
{"learn":[0.1342248155],"iteration":62,"passed_time":0.3448896681,"remaining_time":0.2025542495},
{"learn":[0.1321058406],"iteration":63,"passed_time":0.3501207889,"remaining_time":0.1969429438},
{"learn":[0.1320358509],"iteration":64,"passed_time":0.35540437,"remaining_time":0.1913715838},
{"learn":[0.1307103795],"iteration":65,"passed_time":0.3605167218,"remaining_time":0.1857207355},
{"learn":[0.1277763465],"iteration":66,"passed_time":0.3652034881,"remaining_time":0.1798763449},
{"learn":[0.1255987225],"iteration":67,"passed_time":0.370242077,"remaining_time":0.1742315657},
{"learn":[0.1243594173],"iteration":68,"passed_time":0.3750674954,"remaining_time":0.1685085849},
{"learn":[0.1240991819],"iteration":69,"passed_time":0.3798457132,"remaining_time":0.16279102},
{"learn":[0.1240180237],"iteration":70,"passed_time":0.3848013437,"remaining_time":0.1571723798},
{"learn":[0.1230154862],"iteration":71,"passed_time":0.3899537102,"remaining_time":0.1516486651},
{"learn":[0.1218037489],"iteration":72,"passed_time":0.3951347637,"remaining_time":0.1461457345},
{"learn":[0.119724941],"iteration":73,"passed_time":0.4003410168,"remaining_time":0.1406603572},
{"learn":[0.1185431061],"iteration":74,"passed_time":0.4056883742,"remaining_time":0.1352294581},
{"learn":[0.1184314648],"iteration":75,"passed_time":0.4107074098,"remaining_time":0.1296970768},
{"learn":[0.1181911682],"iteration":76,"passed_time":0.415500704,"remaining_time":0.1241105999},
{"learn":[0.1181198955],"iteration":77,"passed_time":0.4202456801,"remaining_time":0.1185308329},
{"learn":[0.1159337783],"iteration":78,"passed_time":0.4254381968,"remaining_time":0.1130911662},
{"learn":[0.1141718726],"iteration":79,"passed_time":0.4304573091,"remaining_time":0.1076143273},
{"learn":[0.1132229792],"iteration":80,"passed_time":0.4356166517,"remaining_time":0.1021816837},
{"learn":[0.1107128846],"iteration":81,"passed_time":0.4406566063,"remaining_time":0.09672949895},
{"learn":[0.1081033002],"iteration":82,"passed_time":0.4455510434,"remaining_time":0.09125744263},
{"learn":[0.1068754581],"iteration":83,"passed_time":0.4504012546,"remaining_time":0.08579071517},
{"learn":[0.1049339443],"iteration":84,"passed_time":0.4552184589,"remaining_time":0.08033266922},
{"learn":[0.1048442357],"iteration":85,"passed_time":0.4600691797,"remaining_time":0.07489498275},
{"learn":[0.1037804587],"iteration":86,"passed_time":0.4648062356,"remaining_time":0.06945380532},
{"learn":[0.1037277049],"iteration":87,"passed_time":0.4695899687,"remaining_time":0.06403499574},
{"learn":[0.1020797286],"iteration":88,"passed_time":0.4745239022,"remaining_time":0.05864902162},
{"learn":[0.1002305945],"iteration":89,"passed_time":0.4802160158,"remaining_time":0.05335733509},
{"learn":[0.09852759919],"iteration":90,"passed_time":0.4856902232,"remaining_time":0.0480352968},
{"learn":[0.09787393534],"iteration":91,"passed_time":0.4903233006,"remaining_time":0.04263680875},
{"learn":[0.09692477564],"iteration":92,"passed_time":0.4951349654,"remaining_time":0.0372682232},
{"learn":[0.09624193535],"iteration":93,"passed_time":0.499829441,"remaining_time":0.03190400687},
{"learn":[0.09495099033],"iteration":94,"passed_time":0.504789622,"remaining_time":0.02656787484},
{"learn":[0.09417210447],"iteration":95,"passed_time":0.5092700874,"remaining_time":0.02121958698},
{"learn":[0.09355199396],"iteration":96,"passed_time":0.5139889408,"remaining_time":0.01589656518},
{"learn":[0.0926689153],"iteration":97,"passed_time":0.5186537891,"remaining_time":0.01058477121},
{"learn":[0.09259287551],"iteration":98,"passed_time":0.5234143486,"remaining_time":0.005287013622},
{"learn":[0.09213163724],"iteration":99,"passed_time":0.5280722976,"remaining_time":0}
]}